micropython_ds3502/__init__.py
micropython_ds3502/ds3502.py
micropython_ds3502/i2c_helpers.py
micropython_ds3502-0.1.2.dist-info/LICENSE
micropython_ds3502-0.1.2.dist-info/METADATA
micropython_ds3502-0.1.2.dist-info/WHEEL
micropython_ds3502-0.1.2.dist-info/top_level.txt
micropython_ds3502-0.1.2.dist-info/RECORD
