Metadata-Version: 2.1
Name: micropython-ds3502
Version: 0.1.2
Summary: MicroPython Driver for the DS3502 Potentiometer
Author-email: JDM <xxyx@mailmeto.mozmail.com>
License: MIT
Project-URL: Homepage, https://github.com/jposada202020/MicroPython_DS3502
Keywords: sensor,ds3502,potentiometer,resistance,variable,driver,micropython,maxim
Classifier: Intended Audience :: Developers
Classifier: Topic :: Software Development :: Libraries
Classifier: Topic :: Software Development :: Embedded Systems
Classifier: Topic :: System :: Hardware
Classifier: License :: OSI Approved :: MIT License
Classifier: Programming Language :: Python :: Implementation :: MicroPython
License-File: LICENSE
